LICENSE
MANIFEST.in
README.md
setup.py
arspb/__init__.py
arspb/ars.py
arspb/env_utils.py
arspb/filter.py
arspb/logz.py
arspb/lqr_env.py
arspb/optimizers.py
arspb/policies.py
arspb/run_policy.py
arspb/shared_noise.py
arspb/utils.py
arspb.egg-info/PKG-INFO
arspb.egg-info/SOURCES.txt
arspb.egg-info/dependency_links.txt
arspb.egg-info/requires.txt
arspb.egg-info/top_level.txt
arspb/trained_policies/__init__.py
arspb/trained_policies/AntBulletEnv-v0/__init__.py
arspb/trained_policies/AntBulletEnv-v0/nn_policy_plus.npz
arspb/trained_policies/AntBulletEnv-v0/params.json
arspb/trained_policies/CartPoleContinuousBulletEnv-v0/__init__.py
arspb/trained_policies/CartPoleContinuousBulletEnv-v0/lin_policy_plus.npz
arspb/trained_policies/CartPoleContinuousBulletEnv-v0/log.txt
arspb/trained_policies/CartPoleContinuousBulletEnv-v0/params.json
arspb/trained_policies/HumanoidBulletEnv-v0/__init__.py
arspb/trained_policies/HumanoidBulletEnv-v0/nn_policy_plus.npz
arspb/trained_policies/HumanoidBulletEnv-v0/params.json
arspb/trained_policies/HumanoidBulletEnv-v0/spin_run.png
arspb/trained_policies/InvertedPendulumSwingupBulletEnv-v0/__init__.py
arspb/trained_policies/InvertedPendulumSwingupBulletEnv-v0/log.txt
arspb/trained_policies/InvertedPendulumSwingupBulletEnv-v0/nn_policy_plus.npz
arspb/trained_policies/InvertedPendulumSwingupBulletEnv-v0/params.json